tracklet_parser/__init__.py
tracklet_parser/tracklet.py
tracklet_parser/tracklet_parser.py
tracklet_parser-1.1.0.dist-info/METADATA
tracklet_parser-1.1.0.dist-info/WHEEL
tracklet_parser-1.1.0.dist-info/licenses/LICENSE.txt
tracklet_parser-1.1.0.dist-info/RECORD
