Metadata-Version: 2.4
Name: tracklet_parser
Version: 1.1.0
Summary: A parser for tracklet labels in KITTI Raw Format 1.0 created by the Computer Vision Annotation Tool (CVAT).
Project-URL: repository, https://github.com/holtvogt/tracklet_parser
Project-URL: issues, https://github.com/holtvogt/tracklet_parser/issues
Project-URL: changelog, https://github.com/holtvogt/tracklet_parser/blob/develop/CHANGELOG.md
Maintainer-email: Bjoern Holtvogt <bjoern.holtvogt@gmail.com>
License: MIT License
License-File: LICENSE.txt
Keywords: annotation,cvat,kitti,tracklet
Classifier: Development Status :: 4 - Beta
Classifier: Intended Audience :: Developers
Classifier: License :: OSI Approved :: MIT License
Classifier: Programming Language :: Python :: 3.10
Classifier: Topic :: Software Development
Requires-Python: >=3.12
Requires-Dist: black
Requires-Dist: codespell
Requires-Dist: docformatter
Requires-Dist: isort
Requires-Dist: numpy
Requires-Dist: pandas
Requires-Dist: pre-commit
Requires-Dist: pylint
Requires-Dist: wheel
